{
  "main": {
    "id": "5324373015726ba8",
    "type": "split",
    "children": [
      {
        "id": "660f5c03b88d3ca4",
        "type": "tabs",
        "children": [
          {
            "id": "3aeb5449baf9bd3d",
            "type": "leaf",
            "state": {
              "type": "markdown",
              "state": {
                "file": "Notes/Bayesian Networks.md",
                "mode": "preview",
                "source": false
              },
              "icon": "lucide-file",
              "title": "Bayesian Networks"
            }
          }
        ]
      }
    ],
    "direction": "vertical"
  },
  "left": {
    "id": "8808ebc6dba64580",
    "type": "split",
    "children": [
      {
        "id": "b26fffb9f1892e6c",
        "type": "tabs",
        "children": [
          {
            "id": "b2b95e4a4b3af9f4",
            "type": "leaf",
            "state": {
              "type": "bookmarks",
              "state": {},
              "icon": "lucide-bookmark",
              "title": "Bookmarks"
            }
          },
          {
            "id": "d8f75e9e67352fd5",
            "type": "leaf",
            "state": {
              "type": "search",
              "state": {
                "query": "tag:#fysik",
                "matchingCase": false,
                "explainSearch": false,
                "collapseAll": false,
                "extraContext": false,
                "sortOrder": "alphabetical"
              },
              "icon": "lucide-search",
              "title": "Search"
            }
          },
          {
            "id": "399882d0679f2f8c",
            "type": "leaf",
            "state": {
              "type": "file-explorer",
              "state": {
                "sortOrder": "alphabetical",
                "autoReveal": false
              },
              "icon": "lucide-folder-closed",
              "title": "Files"
            }
          }
        ],
        "currentTab": 2
      }
    ],
    "direction": "horizontal",
    "width": 582.5024089813232,
    "collapsed": true
  },
  "right": {
    "id": "5c628f1454f33c40",
    "type": "split",
    "children": [
      {
        "id": "176c1f43f7b4caf8",
        "type": "tabs",
        "children": [
          {
            "id": "21f5d70ac4ad50ad",
            "type": "leaf",
            "state": {
              "type": "backlink",
              "state": {
                "file": "HOME.md",
                "collapseAll": false,
                "extraContext": false,
                "sortOrder": "alphabetical",
                "showSearch": false,
                "searchQuery": "",
                "backlinkCollapsed": false,
                "unlinkedCollapsed": true
              },
              "icon": "links-coming-in",
              "title": "Backlinks for HOME"
            }
          },
          {
            "id": "97beb8ab16acbcef",
            "type": "leaf",
            "state": {
              "type": "outgoing-link",
              "state": {
                "linksCollapsed": false,
                "unlinkedCollapsed": true
              },
              "icon": "lucide-ghost",
              "title": "outgoing-link"
            }
          },
          {
            "id": "bf1ce4279832d89f",
            "type": "leaf",
            "state": {
              "type": "tag",
              "state": {
                "sortOrder": "frequency",
                "useHierarchy": true
              },
              "icon": "lucide-tags",
              "title": "Tags"
            }
          },
          {
            "id": "4a0c4e0ffd11cf56",
            "type": "leaf",
            "state": {
              "type": "mathpad-view",
              "state": {},
              "icon": "sigma",
              "title": "Mathpad"
            }
          },
          {
            "id": "72d5b738631d9762",
            "type": "leaf",
            "state": {
              "type": "all-properties",
              "state": {
                "sortOrder": "frequency",
                "showSearch": false,
                "searchQuery": ""
              },
              "icon": "lucide-archive",
              "title": "All properties"
            }
          },
          {
            "id": "9ca4190a5413d239",
            "type": "leaf",
            "state": {
              "type": "note-chat-view",
              "state": {},
              "icon": "lucide-ghost",
              "title": "note-chat-view"
            }
          },
          {
            "id": "b0337735c4930af8",
            "type": "leaf",
            "state": {
              "type": "advanced-tables-toolbar",
              "state": {},
              "icon": "spreadsheet",
              "title": "Advanced Tables"
            }
          },
          {
            "id": "0b5dfe39c5c75396",
            "type": "leaf",
            "state": {
              "type": "outline",
              "state": {
                "file": "Images/Pasted image 20240912084607.png",
                "followCursor": false,
                "showSearch": false,
                "searchQuery": ""
              },
              "icon": "lucide-list",
              "title": "Outline of Pasted image 20240912084607"
            }
          }
        ]
      }
    ],
    "direction": "horizontal",
    "width": 300,
    "collapsed": true
  },
  "left-ribbon": {
    "hiddenItems": {
      "bases:Create new base": false,
      "switcher:Open quick switcher": false,
      "graph:Open graph view": false,
      "canvas:Create new canvas": false,
      "command-palette:Open command palette": false,
      "table-editor-obsidian:Advanced Tables Toolbar": false,
      "homepage:Open homepage": false,
      "mathpad:Open Mathpad": false,
      "obsidian-excalidraw-plugin:Create new drawing": false,
      "templater-obsidian:Templater": false,
      "obsidian-file-cleaner:Clean files": false,
      "obsidian-git:Open Git source control": false,
      "obsidian-shellcommands:Shell commands: Custom variables": false
    }
  },
  "active": "3aeb5449baf9bd3d",
  "lastOpenFiles": [
    "HOME.md",
    "Notes/Multivariable Math.md",
    "Notes/Classification of Second order PDEs.md",
    "Notes/Kinematrics.md",
    "Notes/Angle-Set Conventions.md",
    "Notes/Transistorer.md",
    "Notes/Dioder.md",
    "Notes/Transistorer.md~",
    "External/Kasper's Notes/Uni/Notes/NewNotes/Kandidat ideer.md",
    "Lessons/Semester 3/signalbehandling/Slides/lektion 8 - Introduktion til IIR filtre.pdf",
    "Lessons/Semester 3/signalbehandling/Slides/Lektion 6 - Systemanalyse i z-domæne.pdf",
    "Lessons/Semester 3/signalbehandling/Slides/Lektion 2 - Sampling og Rekonstruktion.pdf",
    "External/Kasper's Notes/Uni/Slides/utf-8''2025-10-29_20Reproducible_20research_2C_20slides.pdf",
    "External/Kasper's Notes/Uni/Slides/fixed_wings_dynamics.pdf",
    "External/Kasper's Notes/Uni/Slides/_idt_module_6-1.pdf",
    "External/Kasper's Notes/Uni/Slides/_CAS-2025-Lecture7-obs.pdf",
    "External/Kasper's Notes/Uni/Slides/_CAS-2025-Lecture7-LectureNotes.pdf",
    "External/Kasper's Notes/Uni/Slides/_CAS-2025-Lecture6-MPC-fdblin.pdf",
    "External/Kasper's Notes/Uni/Slides/State estimation and Observers.md",
    "External/Kasper's Notes/Uni/Slides/Sensorimotor integration.md",
    "External/Kasper's Notes/Uni/Slides/Reproducible research and R guide.md",
    "External/Kasper's Notes/Uni/Slides/Model Predictive Control.md",
    "External/Kasper's Notes/Uni/Slides/Fixed Wing Dynamics.md",
    "External/Kasper's Notes/Uni/Slides/ADRC.md",
    "External/Kasper's Notes/Uni/Notes/NewNotes/linux connect to wifi.md",
    "External/Kasper's Notes/Uni/Notes/NewNotes/UART to BRAM FPGA.md",
    "External/Kasper's Notes/Uni/Notes/NewNotes/State estimation and observers notes.md",
    "External/Kasper's Notes/Uni/Notes/NewNotes/Quadratic Programming.md",
    "External/Kasper's Notes/Uni/Notes/NewNotes/Output feedback using observer.md",
    "External/Kasper's Notes/Uni/Notes/NewNotes/Model-Predictive Control.md",
    "External/Kasper's Notes/Uni/Notes/NewNotes/Model Predictive Control.md",
    "External/Kasper's Notes/Uni/Notes/NewNotes/Linux Void Todo.md",
    "External/Kasper's Notes/Uni/Notes/NewNotes/Lazyvim CMake.md",
    "External/Kasper's Notes/Uni/Notes/NewNotes/Latex templates.md",
    "External/Kasper's Notes/Uni/Notes/NewNotes/Kandidat projekt ide.md",
    "External/Kasper's Notes/Uni/Exercises/states and observation exercise.md",
    "External/Kasper's Notes/Misc og Links/statefeedback.png",
    "External/Kasper's Notes/Misc og Links/opg4.png",
    "External/Kasper's Notes/Misc og Links/opg3.png",
    "External/Kasper's Notes/Misc og Links/Pasted image 20251117145537.png",
    "External/Kasper's Notes/Misc og Links/Pasted image 20251110143032.png",
    "External/Kasper's Notes/Misc og Links/Pasted image 20251027123250.png",
    "External/Kasper's Notes/Misc og Links/Pasted image 20251026170439.png",
    "External/Kasper's Notes/Misc og Links/Pasted image 20251026163428.png",
    "External/Kasper's Notes/Misc og Links/d20_flat.png",
    "External/Kasper's Notes/Misc og Links/Pasted image 20250923235207.png",
    "Untitled.canvas"
  ]
}