{
  "main": {
    "id": "13e6a3d7ee002d03",
    "type": "split",
    "children": [
      {
        "id": "276d35daed0f4635",
        "type": "tabs",
        "children": [
          {
            "id": "1a63b81e7ac125f2",
            "type": "leaf",
            "state": {
              "type": "markdown",
              "state": {
                "file": "Notes/Control System Performance.md",
                "mode": "preview",
                "source": false
              }
            }
          }
        ]
      }
    ],
    "direction": "vertical"
  },
  "left": {
    "id": "8808ebc6dba64580",
    "type": "split",
    "children": [
      {
        "id": "b26fffb9f1892e6c",
        "type": "tabs",
        "children": [
          {
            "id": "524de691a50000f6",
            "type": "leaf",
            "state": {
              "type": "file-explorer",
              "state": {
                "sortOrder": "alphabetical"
              }
            }
          },
          {
            "id": "655cf959f6798095",
            "type": "leaf",
            "state": {
              "type": "starred",
              "state": {}
            }
          },
          {
            "id": "b2b95e4a4b3af9f4",
            "type": "leaf",
            "state": {
              "type": "bookmarks",
              "state": {}
            }
          },
          {
            "id": "d8f75e9e67352fd5",
            "type": "leaf",
            "state": {
              "type": "search",
              "state": {
                "query": "",
                "matchingCase": false,
                "explainSearch": false,
                "collapseAll": false,
                "extraContext": false,
                "sortOrder": "alphabetical"
              }
            }
          }
        ],
        "currentTab": 3
      }
    ],
    "direction": "horizontal",
    "width": 327.5055751800537,
    "collapsed": true
  },
  "right": {
    "id": "5c628f1454f33c40",
    "type": "split",
    "children": [
      {
        "id": "176c1f43f7b4caf8",
        "type": "tabs",
        "children": [
          {
            "id": "21f5d70ac4ad50ad",
            "type": "leaf",
            "state": {
              "type": "backlink",
              "state": {
                "file": "Notes/Control System Performance.md",
                "collapseAll": false,
                "extraContext": false,
                "sortOrder": "alphabetical",
                "showSearch": false,
                "searchQuery": "",
                "backlinkCollapsed": false,
                "unlinkedCollapsed": true
              }
            }
          },
          {
            "id": "97beb8ab16acbcef",
            "type": "leaf",
            "state": {
              "type": "outgoing-link",
              "state": {
                "linksCollapsed": false,
                "unlinkedCollapsed": true
              }
            }
          },
          {
            "id": "bf1ce4279832d89f",
            "type": "leaf",
            "state": {
              "type": "tag",
              "state": {
                "sortOrder": "frequency",
                "useHierarchy": true
              }
            }
          },
          {
            "id": "3b17a2a4e3705734",
            "type": "leaf",
            "state": {
              "type": "Strange New Worlds",
              "state": {}
            }
          },
          {
            "id": "4a0c4e0ffd11cf56",
            "type": "leaf",
            "state": {
              "type": "mathpad-view",
              "state": {}
            }
          },
          {
            "id": "72d5b738631d9762",
            "type": "leaf",
            "state": {
              "type": "all-properties",
              "state": {
                "sortOrder": "frequency",
                "showSearch": false,
                "searchQuery": ""
              }
            }
          },
          {
            "id": "9ca4190a5413d239",
            "type": "leaf",
            "state": {
              "type": "note-chat-view",
              "state": {}
            }
          },
          {
            "id": "b0337735c4930af8",
            "type": "leaf",
            "state": {
              "type": "advanced-tables-toolbar",
              "state": {}
            }
          },
          {
            "id": "0b5dfe39c5c75396",
            "type": "leaf",
            "state": {
              "type": "outline",
              "state": {
                "file": "Notes/Control System Performance.md"
              }
            }
          }
        ],
        "currentTab": 2
      }
    ],
    "direction": "horizontal",
    "width": 300,
    "collapsed": true
  },
  "left-ribbon": {
    "hiddenItems": {
      "switcher:Open quick switcher": false,
      "graph:Open graph view": false,
      "canvas:Create new canvas": false,
      "command-palette:Open command palette": false,
      "table-editor-obsidian:Advanced Tables Toolbar": false,
      "homepage:Open homepage": false,
      "mathpad:Open Mathpad": false,
      "obsidian-excalidraw-plugin:Create new drawing": false,
      "templater-obsidian:Templater": false,
      "obsidian-file-cleaner:Clean files": false
    }
  },
  "active": "1a63b81e7ac125f2",
  "lastOpenFiles": [
    "Lessons/Semester 4/regulation/Lecture 5 - Root Locus.pdf",
    "Notes/Control System Performance.md",
    "Notes/Komplekse Tal.md",
    "Notes/Bode Plot.md",
    "Lessons/Semester 4/regulation/Lecture 6 - Nyquist Stability Criterion.pdf",
    "Lessons/Semester 4/regulation/Lecture 2 - Stability Analysis.pdf",
    "Notes/Control System Performance.md~",
    "Notes/Laplace Transformation.md",
    "Notes/Signal Processing.md",
    "HOME.md",
    "External/Kasper's Notes/Excalidraw/Drawing 2024-06-01 11.11.40.excalidraw.md",
    "External/Kasper's Notes/Forstærkningsteknik/Noter/Maksimal fejl i forstærkning.md",
    "External/Kasper's Notes/Forstærkningsteknik/Noter/Common Mode Rejection (CMR).md",
    "Lessons/Semester 4/regulation/Lecture 10 - Observers.pdf",
    "Notes/Integral Control.md",
    "Lessons/Semester 4/regulation/Lecture 11 - Integral Control.pdf",
    "Integral Control.md",
    "Pasted image 20240519161915.png",
    "Pasted image 20240519161540.png",
    "Pasted image 20240519161514.png",
    "Pasted image 20240519161430.png",
    "Notes/Anti-Windup.md",
    "Lessons/Semester 4/regulation/integral_control.png",
    "Lessons/Semester 4/Lektion 6.pdf",
    "Lessons/Semester 4/Elektronik/Noter lektion 2.pdf",
    "External/Kasper's Notes/Misc og Links/Pasted image 20240515113013.png",
    "External/Kasper's Notes/Reguleringsteknik/Noter/Full Order Observer.md",
    "Notes/Fejlberegning på Operationsforstærker.md",
    "Notes/Operationsforstærker.md",
    "External/Kasper's Notes/Reguleringsteknik/Noter/Kalman Filter & Random Variables.md",
    "External/Kasper's Notes/Misc og Links/Pasted image 20240503132628.png",
    "External/Kasper's Notes/Misc og Links/Pasted image 20240503132623.png",
    "External/Kasper's Notes/Misc og Links/Pasted image 20240503132619.png",
    "External/Kasper's Notes/Misc og Links/Pasted image 20240503132613.png",
    "Notes/Random Variables.md",
    "Notes/Kalman Filter.md",
    "Notes/Covariance.md",
    "Covariance.md",
    "Kalman Filter.md",
    "Notes/Matricer.md",
    "Notes/Normalfordelingen.md",
    "Lessons/Semester 4/regulation/Lecture 8 - Implementation.pdf",
    "Notes/Normalkraft.md",
    "Random Variables.md",
    "Lessons/Semester 4/regulation/Lecture 12 - The KalmanFilter.pdf",
    "Untitled.canvas"
  ]
}